AudAugio-0.0.2a0.dist-info/METADATA
AudAugio-0.0.2a0.dist-info/RECORD
AudAugio-0.0.2a0.dist-info/WHEEL
AudAugio-0.0.2a0.dist-info/top_level.txt
audaugio/__init__.py
audaugio/augmentation/__init__.py
audaugio/augmentation/augmentation_base.py
audaugio/augmentation/background.py
audaugio/augmentation/equalizer.py
audaugio/augmentation/pitch_shift.py
audaugio/augmentation/time_stretch.py
audaugio/augmentation/windowing.py
audaugio/chain/__init__.py
audaugio/chain/chain_base.py
audaugio/chain/combinatoric.py
audaugio/chain/flat.py
audaugio/chain/linear.py
tests/__init__.py
tests/test_augmentors.py
tests/test_chain.py
