Metadata-Version: 2.1
Name: AudAugio
Version: 0.0.2a0
Summary: Augments audio for machine learning
Home-page: https://github.com/BrianMargolis/AudAugio
Author: Brian Margolis
Author-email: BrianMargolis2019@u.northwestern.edu
License: UNKNOWN
Platform: UNKNOWN
Classifier: Development Status :: 3 - Alpha
Classifier: Programming Language :: Python :: 3
Classifier: License :: OSI Approved :: MIT License
Classifier: Operating System :: OS Independent
Requires-Python: >=3.0
Requires-Dist: librosa
Requires-Dist: numpy
Requires-Dist: sox
